llama_index/storage/kvstore/elasticsearch/__init__.py
llama_index/storage/kvstore/elasticsearch/base.py
llama_index_storage_kvstore_elasticsearch-0.4.1.dist-info/METADATA
llama_index_storage_kvstore_elasticsearch-0.4.1.dist-info/WHEEL
llama_index_storage_kvstore_elasticsearch-0.4.1.dist-info/licenses/LICENSE
llama_index_storage_kvstore_elasticsearch-0.4.1.dist-info/RECORD
