Metadata-Version: 2.4
Name: llama-index-storage-kvstore-elasticsearch
Version: 0.4.1
Summary: llama-index kvstore elasticsearch integration
Author-email: Your Name <you@example.com>
License-Expression: MIT
License-File: LICENSE
Requires-Python: <4.0,>=3.9
Requires-Dist: elasticsearch<9,>=8.12.1
Requires-Dist: llama-index-core<0.15,>=0.13.0
